selenium_configurator/__init__.py
selenium_configurator/configurator.py
selenium_configurator/driver.py
selenium_configurator/drivers/__init__.py
selenium_configurator/drivers/local.py
selenium_configurator/drivers/remote.py
selenium_configurator-0.1.1.dist-info/LICENSE
selenium_configurator-0.1.1.dist-info/METADATA
selenium_configurator-0.1.1.dist-info/WHEEL
selenium_configurator-0.1.1.dist-info/top_level.txt
selenium_configurator-0.1.1.dist-info/RECORD
