Metadata-Version: 1.1
Name: selenium-configurator
Version: 0.1.1
Summary: Helper API to define multiple webdrivers in config files.
Home-page: https://github.com/anybox/selenium-configurator
Author: Pierre Verkest
Author-email: pverkest@anybox.fr
License: LGPL-3.0
Keywords: nose selenium CI
Platform: UNKNOWN
Classifier: Development Status :: 2 - Pre-Alpha
Classifier: Intended Audience :: Developers
Classifier: License :: OSI Approved :: GNU Lesser General Public License v3 or later (LGPLv3+)
Classifier: Operating System :: OS Independent
Classifier: Topic :: Software Development :: Quality Assurance
Classifier: Topic :: Software Development :: Testing
Classifier: Topic :: Utilities
Classifier: Programming Language :: Python
Classifier: Programming Language :: Python :: 2.7
Classifier: Programming Language :: Python :: 3.5
Classifier: Programming Language :: Python :: 3.7
